Workbook

Sheet Historical
A1: CN Rail | Historical Financials (5-Year) | CAD $mm
A2: Source: CN Annual Reports 2021–2025, SEC EDGAR — www.cn.ca/investors
C3: 2021 | D3: 2022 | E3: 2023 | F3: 2024 | G3: 2025
A4: INCOME STATEMENT
A5: Total Revenue | C5: 14477 | D5: 17107 | E5: 16828 | F5: 17046 | G5: 17300 | H5: Source: CN Annual Reports, Selected Railroad Statistics
A6: Operating Income (EBIT) | C6: 5616 | D6: 6840 | E6: 6597 | F6: 6247 | G6: 6600 | H6: Source: same
A7: EBIT Margin % | C7: =C6/C5 -> 0.38792568 | D7: =D6/D5 -> 0.39983632 | E7: =E6/E5 -> 0.3920252 | F7: =F6/F5 -> 0.36647894 | G7: =G6/G5 -> 0.38150289 | H7: Formula: EBIT / Revenue
A8: Net Income | C8: 4899 | D8: 5118 | E8: 5625 | F8: 4448 | G8: 4700 | H8: Source: same
A9: Net Margin % | C9: =C8/C5 -> 0.33839884 | D9: =D8/D5 -> 0.29917578 | E9: =E8/E5 -> 0.33426432 | F9: =F8/F5 -> 0.26094098 | G9: =G8/G5 -> 0.2716763 | H9: Formula: Net Income / Revenue
A10: Diluted EPS ($) | C10: 6.89 | D10: 7.44 | E10: 8.53 | F10: 7.01 | G10: 7.57 | H10: Source: same
A11: Operating Ratio % | C11: 0.612 | D11: 0.6 | E11: 0.608 | F11: 0.634 | G11: 0.619 | H11: Source: same
A12: CASH FLOW & CAPEX
A13: Free Cash Flow | C13: 3296 | D13: 4259 | E13: 3887 | F13: 3092 | G13: 3340 | H13: Source: CN Annual Reports
A14: Gross Capex | C14: 2639 | D14: 2757 | E14: 3217 | F14: 3549 | G14: 3300 | H14: Source: same
A15: FCF Conversion % | C15: =C13/C8 -> 0.67279037 | D15: =D13/D8 -> 0.832161 | E15: =E13/E8 -> 0.69102222 | F15: =F13/F8 -> 0.69514388 | G15: =G13/G8 -> 0.7106383 | H15: Formula: FCF / Net Income
A16: Capex % of Revenue | C16: =C14/C5 -> 0.18228915 | D16: =D14/D5 -> 0.1611621 | E16: =E14/E5 -> 0.19116948 | F16: =F14/F5 -> 0.20820134 | G16: =G14/G5 -> 0.19075145 | H16: Formula: Capex / Revenue
A17: ADDITIONAL METRICS
A18: D&A (Depreciation & Amortization) | C18: 1598 | D18: 1729 | E18: 1817 | F18: 1892 | G18: 1938
A19: EBITDA | C19: =C6+C18 -> 7214 | D19: =D6+D18 -> 8569 | E19: =E6+E18 -> 8414 | F19: =F6+F18 -> 8139 | G19: =G6+G18 -> 8538
A20: EBITDA Margin % | C20: =C19/C5 -> 0.49830766 | D20: =D19/D5 -> 0.50090606 | E20: =E19/E5 -> 0.5 | F20: =F19/F5 -> 0.47747272 | G20: =G19/G5 -> 0.49352601
A21: Interest Expense | C21: 610 | D21: 548 | E21: 722 | F21: 891 | G21: 913
A22: Income Tax Expense | C22: 1443 | D22: 1645 | E22: 1443 | F22: 1404 | G22: 1544
A23: Effective Tax Rate % | C23: =C22/(C6-C21) -> 0.2882541 | D23: =D22/(D6-D21) -> 0.2614431 | E23: =E22/(E6-E21) -> 0.24561702 | F23: =F22/(F6-F21) -> 0.26213592 | G23: =G22/(G6-G21) -> 0.2714964
A24: BALANCE SHEET ITEMS
A25: Long-Term Debt | C25: 11977 | D25: 14372 | E25: 16133 | F25: 19728 | G25: 20300
A26: Current Portion of LT Debt | C26: 508 | D26: 1057 | E26: 2340 | F26: 1166 | G26: 906
A27: Total Debt | C27: =C25+C26 -> 12485 | D27: =D25+D26 -> 15429 | E27: =E25+E26 -> 18473 | F27: =F25+F26 -> 20894 | G27: =G25+G26 -> 21206
A28: Shares Outstanding (mm) | C28: 700.9 | D28: 671 | E28: 642.7 | F28: 627.9 | G28: 613.3

Sheet Assumptions
A1: CN Rail DCF | Assumptions
B2: 2021 | C2: 2022 | D2: 2023 | E2: 2024 | F2: 2025 | G2: 5yr Avg | H2: Assumption | I2: Reasoning
A3: Revenue Growth % | B3: – | C3: =(Historical!D5-Historical!C5)/Historical!C5 -> 0.18166747 | D3: =(Historical!E5-Historical!D5)/Historical!D5 -> -0.016309113 | E3: =(Historical!F5-Historical!E5)/Historical!E5 -> 0.012954599 | F3: =(Historical!G5-Historical!F5)/Historical!F5 -> 0.014900857 | G3: =AVERAGE(C3:F3) -> 0.048303454 | H3: 0.02 | I3: 3-year avg excluding 2022 (COVID) ~ 1.4%, anchored to long-run North American GDP growth of 2%
A4: EBITDA Margin % | B4: =Historical!C20 -> 0.49830766 | C4: =Historical!D20 -> 0.50090606 | D4: =Historical!E20 -> 0.5 | E4: =Historical!F20 -> 0.47747272 | F4: =Historical!G20 -> 0.49352601 | G4: =AVERAGE(B4:F4) -> 0.49404249 | H4: 0.493 | I4: 5-year avg excluding 2022 COVID outlier
A5: Capex % Revenue | B5: =Historical!C16 -> 0.18228915 | C5: =Historical!D16 -> 0.1611621 | D5: =Historical!E16 -> 0.19116948 | E5: =Historical!F16 -> 0.20820134 | F5: =Historical!G16 -> 0.19075145 | G5: =AVERAGE(B5:F5) -> 0.1867147 | H5: 0.19 | I5: Appears to be stabilizing around this level in recent years
A6: Tax Rate % | B6: =Historical!C23 -> 0.2882541 | C6: =Historical!D23 -> 0.2614431 | D6: =Historical!E23 -> 0.24561702 | E6: =Historical!F23 -> 0.26213592 | F6: =Historical!G23 -> 0.2714964 | G6: =AVERAGE(B6:F6) -> 0.26578931 | H6: 0.27 | I6: High-end of observed range, conservative estimate
A7: DCF-SPECIFIC ASSUMPTIONS — To be derived on DCF sheet
A8: Terminal Growth Rate | H8: 0.02 | I8: In line with long-run North American GDP growth; standard for mature infrastructure
A9: WACC | H9: =DCF!B6 -> 0.075272371 | I9: Calculated on DCF sheet from cost of debt + cost of equity (CAPM)

Sheet Projections
A1: CN Rail DCF | Projected Free Cash Flows | CAD $mm
B2: 2026 | C2: 2027 | D2: 2028 | E2: 2029 | F2: 2030
A3: INCOME
A4: Revenue | B4: =Historical!$G$5*(1+Assumptions!$H$3)^(B2-2025) -> 17646 | C4: =Historical!$G$5*(1+Assumptions!$H$3)^(C2-2025) -> 17998.92 | D4: =Historical!$G$5*(1+Assumptions!$H$3)^(D2-2025) -> 18358.898 | E4: =Historical!$G$5*(1+Assumptions!$H$3)^(E2-2025) -> 18726.076 | F4: =Historical!$G$5*(1+Assumptions!$H$3)^(F2-2025) -> 19100.598
A5: EBITDA | B5: =B4*Assumptions!$H$4 -> 8699.478 | C5: =C4*Assumptions!$H$4 -> 8873.4676 | D5: =D4*Assumptions!$H$4 -> 9050.9369 | E5: =E4*Assumptions!$H$4 -> 9231.9556 | F5: =F4*Assumptions!$H$4 -> 9416.5948
A6: EBITDA Margin % | B6: =B5/B4 -> 0.493 | C6: =C5/C4 -> 0.493 | D6: =D5/D4 -> 0.493 | E6: =E5/E4 -> 0.493 | F6: =F5/F4 -> 0.493
A7: EBIT | B7: =B5-B12 -> 6722.718 | C7: =C5-C12 -> 6857.1724 | D7: =D5-D12 -> 6994.3158 | E7: =E5-E12 -> 7134.2021 | F7: =F5-F12 -> 7276.8862
A8: EBIT Margin % | B8: =B7/B4 -> 0.38097688 | C8: =C7/C4 -> 0.38097688 | D8: =D7/D4 -> 0.38097688 | E8: =E7/E4 -> 0.38097688 | F8: =F7/F4 -> 0.38097688
A10: FREE CASH FLOW
A11: NOPAT | B11: =B7*(1-Assumptions!$H$6) -> 4907.5841 | C11: =C7*(1-Assumptions!$H$6) -> 5005.7358 | D11: =D7*(1-Assumptions!$H$6) -> 5105.8505 | E11: =E7*(1-Assumptions!$H$6) -> 5207.9676 | F11: =F7*(1-Assumptions!$H$6) -> 5312.1269
A12: D&A | B12: =Historical!$G$18*(1+Assumptions!$H$3)^(B2-2025) -> 1976.76 | C12: =Historical!$G$18*(1+Assumptions!$H$3)^(C2-2025) -> 2016.2952 | D12: =Historical!$G$18*(1+Assumptions!$H$3)^(D2-2025) -> 2056.6211 | E12: =Historical!$G$18*(1+Assumptions!$H$3)^(E2-2025) -> 2097.7535 | F12: =Historical!$G$18*(1+Assumptions!$H$3)^(F2-2025) -> 2139.7086
A13: Capex | B13: =B4*Assumptions!$H$5 -> 3352.74 | C13: =C4*Assumptions!$H$5 -> 3419.7948 | D13: =D4*Assumptions!$H$5 -> 3488.1907 | E13: =E4*Assumptions!$H$5 -> 3557.9545 | F13: =F4*Assumptions!$H$5 -> 3629.1136
A14: Unlevered Free Cash Flow | B14: =B11+B12-B13 -> 3531.6041 | C14: =C11+C12-C13 -> 3602.2362 | D14: =D11+D12-D13 -> 3674.2809 | E14: =E11+E12-E13 -> 3747.7666 | F14: =F11+F12-F13 -> 3822.7219
A15: Assumptions: Revenue Growth 2.0% | EBITDA Margin 49.3% | Capex % Rev 19.0% | Tax Rate 27.0%

Sheet DCF
A1: CN Rail DCF | Discounted Cash Flow Valuation | CAD $mm
B2: Share price | C2: 139.75 | D2: CN Rail Beta | E2: 0.95 | F2: Canada 10-yr gov bond yield | G2: 0.03387
A3: WACC COMPONENTS
A4: Cost of Debt | B4: =Historical!G21/Historical!G27*(1-Assumptions!H6) -> 0.031429312
A5: Cost of Equity | B5: =G2 + E2*0.055 -> 0.08612
A6: WACC | B6: =(C2*Historical!G28)/(C2*Historical!G28+Historical!G27) * DCF!B5 + (Historical!G27)/(Historical!G28*C2 + Historical!G27) * DCF!B4 -> 0.075272371
A7: DISCOUNTED CASH FLOWS | B7: 2026 | C7: 2027 | D7: 2028 | E7: 2029 | F7: 2030
A8: Discounted Free Cash Flow | B8: =Projections!B14/(1+DCF!$B$6)^(DCF!B7-2025) -> 3284.381 | C8: =Projections!C14/(1+DCF!$B$6)^(DCF!C7-2025) -> 3115.5535 | D8: =Projections!D14/(1+DCF!$B$6)^(DCF!D7-2025) -> 2955.4043 | E8: =Projections!E14/(1+DCF!$B$6)^(DCF!E7-2025) -> 2803.4872 | F8: =Projections!F14/(1+DCF!$B$6)^(DCF!F7-2025) -> 2659.3792
A9: Terminal Value (undiscounted) | B9: =Projections!F14*(1+Assumptions!H8)/(DCF!B6-Assumptions!H8) -> 70544.763
A10: PV of Terminal Value | B10: =B9/(1+B6)^5 -> 49076.36
A11: Sum of Discounted FCFs | B11: =SUM(B8:F8) -> 14818.205
A12: Implied Share Price | B12: =SUM(B8:F8,B10)/Historical!G28 -> 104.18158
A13: Current Market Price | B13: 139.75
A14: Premium / (Discount) to Market | B14: =(B12-B13)/B13 -> -0.2545146

Sheet Comps
A1: CN Rail DCF | Sensitivity Analysis | Implied Share Price (CAD)
A2: Market price: $139.75 | Base case (7.5% WACC, 2.0% TGR): ~$104 | Green = undervalued | Red = overvalued
A4: IMPLIED SHARE PRICE — WACC (columns) vs Terminal Growth Rate (rows)
A6: TGR \ WACC | B6: 0.065 | C6: 0.07 | D6: 0.075 | E6: 0.08 | F6: 0.085
A7: 0.015 | B7: 117.2 | C7: 106.52 | D7: 97.63 | E7: 90.1 | F7: 83.65
A8: 0.02 | B8: 127.96 | C8: 115.17 | D8: 104.7 | E8: 95.97 | F8: 88.59
A9: 0.025 | B9: 141.42 | C9: 125.73 | D9: 113.18 | E9: 102.91 | F9: 94.36
A10: 0.03 | B10: 158.73 | C10: 138.94 | D10: 123.56 | E10: 111.24 | F10: 101.17
A11: LEGEND: | B11: Green = implied > $139.75 (undervalued) | D11: Red = implied < $139.75 (overvalued) | F11: Blue = base case
A12: CN Rail DCF | Comparable Companies Analysis | TTM Data
A13: Source: Yahoo Finance, StockAnalysis.com | CN Rail in CAD, peers in USD | As of March 2026
A14: Metric | B14: CN Rail | C14: CP Rail | D14: Union Pacific | E14: Norfolk Southern | F14: Peer Avg | G14: CN vs Peers
A15: EV/EBITDA | B15: 12.01 | C15: 15.6 | D15: 15.01 | E15: 13.51 | F15: 14.71 | G15: -0.18336355
A16: P/E Ratio | B16: 19.02 | C16: 25.5 | D16: 21.85 | E16: 17.25 | F16: 21.53 | G16: -0.11671827
A17: EV ($B) | B17: 80.6 | C17: 82 | D17: 175.2 | E17: 79.4 | F17: 112.2 | G17: -0.28163993
A18: EBITDA ($B) | B18: 8.54 | C18: 5.99 | D18: 11.68 | E18: 5.87 | F18: 7.85 | G18: 0.088360238
A19: Net Margin % | B19: 0.273 | C19: 0.284 | D19: 0.291 | E19: 0.275 | F19: 0.28 | G19: -0.036470588
A20: VALUATION SUMMARY
A21: DCF Implied Share Price | B21: 104.18
A22: Current Market Price | B22: 139.75
A23: DCF Premium / (Discount) | B23: -0.254
A24: Analyst Consensus Target | B24: ~$117
